devopstestor/__init__.py
devopstestor/config/arguments.yml
devopstestor/config/core.yml
devopstestor/config/machine.yml
devopstestor/config/provisionner.yml
devopstestor/config/report.yml
devopstestor/config/source_manager.yml
devopstestor/config/testcase.yml
devopstestor/presets/__init__.py
devopstestor/presets/logstash/__init__.py
devopstestor/presets/logstash/__main__.py
devopstestor/presets/logstash/build4docker.bash
devopstestor/presets/logstash/config/arguments.yml
devopstestor/presets/logstash/config/machine.yml
devopstestor/presets/logstash/config/provisionner.yml
devopstestor/presets/logstash/config/report.yml
devopstestor/presets/logstash/config/source_manager.yml
devopstestor/presets/logstash/config/testcase.yml
devopstestor/presets/logstash/machine/entrypoint.sh
devopstestor/presets/logstash/machine/logstash
devopstestor/presets/logstash/testconf/verifiers/.gitkeep
devopstestor/presets/saltstack/__init__.py
devopstestor/presets/saltstack/__main__.py
devopstestor/presets/saltstack/build4docker.bash
devopstestor/presets/saltstack/config/arguments.yml
devopstestor/presets/saltstack/config/machine.yml
devopstestor/presets/saltstack/config/provisionner.yml
devopstestor/presets/saltstack/config/report.yml
devopstestor/presets/saltstack/config/source_manager.yml
devopstestor/presets/saltstack/config/testcase.yml
devopstestor/presets/saltstack/machine/salt-machine-debian
devopstestor/presets/saltstack/machine/ressources/etc/salt/master.d/override.conf
devopstestor/presets/saltstack/machine/ressources/tmp/install_base.bash
devopstestor/presets/saltstack/machine/ressources/usr/lib/python3/dist-packages/salt/modules/sdb.py
devopstestor/presets/saltstack/machine/ressources/usr/lib/python3/dist-packages/salt/runners/sdb.py
devopstestor/presets/saltstack/testconf/verifiers/.gitkeep
devopstestor/src/__init__.py
devopstestor/src/abstract/__init__.py
devopstestor/src/abstract/abstract_machine_controller.py
devopstestor/src/abstract/abstract_provisionner.py
devopstestor-2.2.6.dist-info/licenses/LICENCE
devopstestor-2.2.6.dist-info/METADATA
devopstestor-2.2.6.dist-info/WHEEL
devopstestor-2.2.6.dist-info/top_level.txt
devopstestor-2.2.6.dist-info/RECORD
