Metadata-Version: 2.4
Name: devopstestor
Version: 2.2.6
Summary: Framwork to auto test machine provisioning
Home-page: https://gitlab.com/alexis.porzier.pro/devopstestor
Author: Alexis PORZIER
Author-email: alexis.porzier.pro@gmail.com
Classifier: Programming Language :: Python :: 3.8
Classifier: Operating System :: OS Independent
Requires-Python: >=3.0
License-File: LICENCE
Requires-Dist: pathlib
Requires-Dist: pyyaml
Requires-Dist: pytest-testinfra
Requires-Dist: docker
Requires-Dist: jinja2
Requires-Dist: coloredlogs
Requires-Dist: dateutils
Dynamic: author
Dynamic: author-email
Dynamic: classifier
Dynamic: description
Dynamic: description-content-type
Dynamic: home-page
Dynamic: license-file
Dynamic: requires-dist
Dynamic: requires-python
Dynamic: summary
